LICENSE
MANIFEST.in
README.rst
setup.py
zgitignore.py
test/__init__.py
test/test_zgitignore.py
zgitignore.egg-info/PKG-INFO
zgitignore.egg-info/SOURCES.txt
zgitignore.egg-info/dependency_links.txt
zgitignore.egg-info/top_level.txt