Metadata-Version: 1.1
Name: zgitignore
Version: 0.7
Summary: Check if a file is ignored by a .zgitignore file, compatible with .gitignore syntax
Home-page: https://github.com/zb3/zgitignore
Author: zb3
Author-email: sgv@o2.pl
License: MIT
Keywords: gitignore exclude pattern
Platform: UNKNOWN
Classifier: Development Status :: 3 - Alpha
Classifier: Intended Audience :: Developers
Classifier: License :: OSI Approved :: MIT License
Classifier: Programming Language :: Python :: 2
Classifier: Programming Language :: Python :: 3
Classifier: Topic :: Software Development
